{
  "main": {
    "id": "34cfe389497620bc",
    "type": "split",
    "children": [
      {
        "id": "728c91f582058568",
        "type": "tabs",
        "children": [
          {
            "id": "f56c7c2469b0eec7",
            "type": "leaf",
            "pinned": true,
            "state": {
              "type": "markdown",
              "state": {
                "file": "task/TODO.md",
                "mode": "source",
                "source": false
              },
              "pinned": true,
              "icon": "lucide-file",
              "title": "TODO"
            }
          },
          {
            "id": "585d53d759ad55b4",
            "type": "leaf",
            "pinned": true,
            "state": {
              "type": "markdown",
              "state": {
                "file": "AWS/Serviceメモ.md",
                "mode": "source",
                "source": false
              },
              "pinned": true,
              "icon": "lucide-file",
              "title": "Serviceメモ"
            }
          }
        ],
        "currentTab": 1
      }
    ],
    "direction": "vertical"
  },
  "left": {
    "id": "00ae4636ad8b595f",
    "type": "split",
    "children": [
      {
        "id": "83277010ff00e2d5",
        "type": "tabs",
        "children": [
          {
            "id": "da04bc3e138ed72b",
            "type": "leaf",
            "state": {
              "type": "file-explorer",
              "state": {
                "sortOrder": "alphabetical",
                "autoReveal": false
              },
              "icon": "lucide-folder-closed",
              "title": "ファイルエクスプローラ"
            }
          },
          {
            "id": "7c5b369d02c892e7",
            "type": "leaf",
            "state": {
              "type": "search",
              "state": {
                "query": "lanczos",
                "matchingCase": false,
                "explainSearch": false,
                "collapseAll": false,
                "extraContext": false,
                "sortOrder": "alphabetical"
              },
              "icon": "lucide-search",
              "title": "検索"
            }
          },
          {
            "id": "d048f80fb9fe7abd",
            "type": "leaf",
            "state": {
              "type": "bookmarks",
              "state": {},
              "icon": "lucide-bookmark",
              "title": "ブックマーク"
            }
          }
        ]
      }
    ],
    "direction": "horizontal",
    "width": 200
  },
  "right": {
    "id": "a7dcb39feb5f99a5",
    "type": "split",
    "children": [
      {
        "id": "262af2ea336aee05",
        "type": "tabs",
        "children": [
          {
            "id": "c7fb4f3c75a01e80",
            "type": "leaf",
            "pinned": true,
            "state": {
              "type": "graph",
              "state": {},
              "pinned": true,
              "icon": "lucide-git-fork",
              "title": "グラフビュー"
            }
          },
          {
            "id": "3b8821af81e881fb",
            "type": "leaf",
            "state": {
              "type": "backlink",
              "state": {
                "file": "task/TODO.md",
                "collapseAll": false,
                "extraContext": false,
                "sortOrder": "alphabetical",
                "showSearch": false,
                "searchQuery": "",
                "backlinkCollapsed": false,
                "unlinkedCollapsed": true
              },
              "icon": "links-coming-in",
              "title": "TODOへのバックリンク"
            }
          },
          {
            "id": "66bbe19cd50ef46f",
            "type": "leaf",
            "state": {
              "type": "outgoing-link",
              "state": {
                "file": "task/TODO.md",
                "linksCollapsed": false,
                "unlinkedCollapsed": true
              },
              "icon": "links-going-out",
              "title": "TODOからのアウトゴーイングリンク"
            }
          },
          {
            "id": "2597ebf2cf666769",
            "type": "leaf",
            "state": {
              "type": "tag",
              "state": {
                "sortOrder": "frequency",
                "useHierarchy": true,
                "showSearch": false,
                "searchQuery": ""
              },
              "icon": "lucide-tags",
              "title": "タグ"
            }
          },
          {
            "id": "8917ffcbf331f0ec",
            "type": "leaf",
            "state": {
              "type": "outline",
              "state": {
                "file": "task/TODO.md",
                "followCursor": false,
                "showSearch": false,
                "searchQuery": ""
              },
              "icon": "lucide-list",
              "title": "TODOのアウトライン"
            }
          }
        ]
      }
    ],
    "direction": "horizontal",
    "width": 1040.5,
    "collapsed": true
  },
  "left-ribbon": {
    "hiddenItems": {
      "bases:Create new base": false,
      "obsidian-git:Open Git source control": false,
      "switcher:クイックスイッチャーを開く": false,
      "graph:グラフビューを開く": false,
      "canvas:新規キャンバスを作成": false,
      "daily-notes:今日のデイリーノートを開く": false,
      "templates:テンプレートを挿入": false,
      "command-palette:コマンドパレットを開く": false
    }
  },
  "active": "da04bc3e138ed72b",
  "lastOpenFiles": [
    "セキュリティ対応/日次で話すこと.md",
    "セキュリティ対応/作業細分化・スケジュール出し.md",
    "セキュリティ対応",
    "task/archive/0128 水島本番反映/1225 ENEOS_SPM_MIZUSHIMA-714 【本番】【ENEOS水島】【500エラー】システム管理 > お知らせ：セッションが切れた状態でお知らせの作成をできてしまうことで発生するエラー.md",
    "task/archive/0128 水島本番反映/1225 ENEOS_SPM_MIZUSHIMA-589 【SlowQuery】B画面：工事箇所の仕様 > 機器のプルダウンで発行されるSQL v2.md",
    "task/archive/0128 水島本番反映",
    "task/archive/0127 鹿島本番反映/1225 ENEOS_SPM_KASHIMA-612 鹿島 B 不具合情報 > 請求内容 工事内容 改行されるようにする.md",
    "task/archive/0127 鹿島本番反映/1225 ENEOS_SPM_KASHIMA-447 鹿島 E,F画面 作業完了報告時にファイルの添付機能※堺では実装.md",
    "task/archive/0127 鹿島本番反映",
    "task/archive/0126 麻里布本番反映/1225 ENEOS_SPM_MARIFU-436 麻里布 リンク機能追加 ※鹿島流用.md",
    "task/archive/0126 麻里布本番反映",
    "退寮について.md",
    "作業細分化・スケジュール出し.md",
    "task/archive/当日工事完了の列削除対応.md",
    "task/archive/0116 大分本番反映/1225 ENEOS_SPM_OOITA-109 大分 ログイン画面 パスワード再発行画面 本登録メールを再送できるようにする ※千葉流用.md",
    "task/archive/0116 大分本番反映",
    "task/archive/01 根岸本番反映/1225 ENEOS_SPM_NEGISHI-123 根岸 ログイン画面 パスワード再発行画面 本登録メールを再送できるようにする ※千葉流用.md",
    "task/archive/01 根岸本番反映/1225 ENEOS_SPM_NEGISHI-105 根岸 ネットワーク接続エラー対応 ※堺流用.md",
    "task/archive/01 根岸本番反映",
    "task/0116 大分本番反映/1225 ENEOS_SPM_OOITA-109 大分 ログイン画面 パスワード再発行画面 本登録メールを再送できるようにする ※千葉流用.md",
    "conflict-files-obsidian-git.md",
    "AWS/Serviceメモ.md",
    "S3復旧作業メモ.md",
    "task/週次定例/0109 千葉本番反映/1225 ENEOSCHIBA-182 千葉 ログイン画面 パスワード再発行画面 本登録メールを再送できるようにする.md",
    "task/週次定例/0109 千葉本番反映",
    "task/archive/S3復旧作業メモ.md",
    "川野さんからMTG.md",
    "task/TODO.md",
    "task/0109 千葉本番反映/1225 ENEOSCHIBA-182 千葉 ログイン画面 パスワード再発行画面 本登録メールを再送できるようにする.md",
    "task/0725 Resiaラベリング対応.md",
    "task/0128 水島本番反映/1225 ENEOS_SPM_MIZUSHIMA-589 【SlowQuery】B画面：工事箇所の仕様 > 機器のプルダウンで発行されるSQL v2.md",
    "task/0127 鹿島本番反映/1225 ENEOS_SPM_KASHIMA-612 鹿島 B 不具合情報 > 請求内容 工事内容 改行されるようにする.md",
    "task/0127 鹿島本番反映/1225 ENEOS_SPM_KASHIMA-447 鹿島 E,F画面 作業完了報告時にファイルの添付機能※堺では実装.md",
    "knowledge/機械学習/クラスタリング.avif",
    "knowledge/機械学習",
    "task/0128 水島本番反映",
    "task/01 根岸本番反映",
    "AWS/Services/CloudFormation 1e9817a83f5b80b696ebe4e00a9ee145/スクリーンショット_2025-07-20_16.34.06.png",
    "AWS/Services/CloudTrail_event.png",
    "12778374-908c-4d44-b1e8-b56fd2bca6b1_Export-5e2471c8-4afd-4b68-9812-7f5b0e1f7634/CFL & SAA & SAP 14e817a83f5b80a4b6f8f65dc603b113/CloudTrail 1ab817a83f5b80f98b54f590b267a8fd/スクリーンショット_2025-07-23_0.33.45.png",
    "12778374-908c-4d44-b1e8-b56fd2bca6b1_Export-5e2471c8-4afd-4b68-9812-7f5b0e1f7634/CFL & SAA & SAP 14e817a83f5b80a4b6f8f65dc603b113/CloudFormation 1e9817a83f5b80b696ebe4e00a9ee145/スクリーンショット_2025-07-20_16.34.06.png",
    "CFL & SAA & SAP 14e817a83f5b80a4b6f8f65dc603b113/CloudFormation 1e9817a83f5b80b696ebe4e00a9ee145/スクリーンショット_2025-07-20_16.34.06.png",
    "CFL & SAA & SAP 14e817a83f5b80a4b6f8f65dc603b113/CloudTrail 1ab817a83f5b80f98b54f590b267a8fd/スクリーンショット_2025-07-23_0.33.45.png",
    "無題のファイル.canvas"
  ]
}